{"coffees":[{"id":1671,"roaster_id":6,"roasting_level_id":null,"brewing_method_id":4,"processing_method_id":6,"roasting_date":null,"origin_country_id":4,"origin_region_id":343,"webshop_item_link":"https://sheepandraven.com/en/sklep/black-sheep/colombia-santa-monica-coco-peach-2/","origin_farm_id":4,"price_per_gram":0.47,"is_decaf":0,"weight":200,"price":95,"is_removed":0,"currency":"PLN"},{"id":1585,"roaster_id":82,"roasting_level_id":null,"brewing_method_id":3,"processing_method_id":25,"roasting_date":null,"origin_country_id":9,"origin_region_id":null,"webshop_item_link":"https://shop.spojkaroastery.com/en/products/guru-3","origin_farm_id":null,"price_per_gram":0.06,"is_decaf":0,"weight":200,"price":12,"is_removed":0,"currency":"EUR"},{"id":455,"roaster_id":252,"roasting_level_id":null,"brewing_method_id":1,"processing_method_id":null,"roasting_date":null,"origin_country_id":3,"origin_region_id":1218,"webshop_item_link":"https://meron.ro/en/produs/ethiopia-uraga-250g-heirloom-natural/","origin_farm_id":null,"price_per_gram":0.06,"is_decaf":0,"weight":250,"price":15,"is_removed":0,"currency":"EUR"},{"id":454,"roaster_id":252,"roasting_level_id":null,"brewing_method_id":1,"processing_method_id":null,"roasting_date":null,"origin_country_id":12,"origin_region_id":185,"webshop_item_link":"https://meron.ro/en/produs/honduras-sol-naciente-250g-red-catuai-carbonic-maceration-72h/","origin_farm_id":null,"price_per_gram":0.06,"is_decaf":0,"weight":250,"price":15,"is_removed":0,"currency":"EUR"},{"id":1590,"roaster_id":82,"roasting_level_id":null,"brewing_method_id":3,"processing_method_id":5,"roasting_date":null,"origin_country_id":4,"origin_region_id":null,"webshop_item_link":"https://shop.spojkaroastery.com/en/products/juicy-strawberry","origin_farm_id":null,"price_per_gram":0.1,"is_decaf":0,"weight":200,"price":19,"is_removed":0,"currency":"EUR"},{"id":365,"roaster_id":278,"roasting_level_id":null,"brewing_method_id":3,"processing_method_id":1,"roasting_date":null,"origin_country_id":3,"origin_region_id":null,"webshop_item_link":"https://palecoffee.pl/product/halo-beriti-ethiopia/","origin_farm_id":null,"price_per_gram":0.33,"is_decaf":0,"weight":200,"price":65,"is_removed":0,"currency":"PLN"},{"id":2912,"roaster_id":288,"roasting_level_id":null,"brewing_method_id":1,"processing_method_id":2,"roasting_date":null,"origin_country_id":4,"origin_region_id":null,"webshop_item_link":"https://www.nordbeans.com/colombia_z18/","origin_farm_id":null,"price_per_gram":1.2,"is_decaf":0,"weight":250,"price":300,"is_removed":0,"currency":"CZK"},{"id":725,"roaster_id":6,"roasting_level_id":null,"brewing_method_id":4,"processing_method_id":6,"roasting_date":null,"origin_country_id":4,"origin_region_id":343,"webshop_item_link":"https://sheepandraven.com/en/sklep/black-sheep/colombia-santa-monica-passionfruit-2/","origin_farm_id":4,"price_per_gram":0.47,"is_decaf":0,"weight":200,"price":95,"is_removed":0,"currency":"PLN"},{"id":3601,"roaster_id":288,"roasting_level_id":null,"brewing_method_id":1,"processing_method_id":1,"roasting_date":null,"origin_country_id":2,"origin_region_id":null,"webshop_item_link":"https://www.nordbeans.com/fox-spresso_z3/","origin_farm_id":null,"price_per_gram":1.2,"is_decaf":0,"weight":250,"price":300,"is_removed":0,"currency":"CZK"},{"id":458,"roaster_id":252,"roasting_level_id":null,"brewing_method_id":1,"processing_method_id":null,"roasting_date":null,"origin_country_id":16,"origin_region_id":1223,"webshop_item_link":"https://meron.ro/en/produs/panama-janson-lot-1015-40g-gesha-natural/","origin_farm_id":null,"price_per_gram":0.28,"is_decaf":0,"weight":40,"price":11,"is_removed":0,"currency":"EUR"}],"originCountries":[4,48],"roasters":[11,23,27,35,93,94,234,252,258,280,284],"tasteNoteGroups":[1]}