{"coffees":[{"id":8403,"roaster_id":317,"roasting_level_id":null,"brewing_method_id":3,"processing_method_id":2,"roasting_date":null,"origin_country_id":11,"origin_region_id":null,"webshop_item_link":"https://lencoffee.com/products/kenia-kirura-ab","origin_farm_id":null,"price_per_gram":0.31,"is_decaf":0,"weight":100,"price":31,"is_removed":0,"currency":"PLN"},{"id":7308,"roaster_id":315,"roasting_level_id":null,"brewing_method_id":1,"processing_method_id":1,"roasting_date":null,"origin_country_id":4,"origin_region_id":1227,"webshop_item_link":"https://www.beberrycoffee.cz/produkt/colombia-el-indio/","origin_farm_id":null,"price_per_gram":1.44,"is_decaf":0,"weight":250,"price":359,"is_removed":0,"currency":"CZK"},{"id":5223,"roaster_id":286,"roasting_level_id":null,"brewing_method_id":1,"processing_method_id":1,"roasting_date":null,"origin_country_id":2,"origin_region_id":null,"webshop_item_link":"https://stow.si/en/izdelek/pau/","origin_farm_id":null,"price_per_gram":0.05,"is_decaf":0,"weight":250,"price":11.9,"is_removed":0,"currency":"EUR"},{"id":7856,"roaster_id":287,"roasting_level_id":null,"brewing_method_id":3,"processing_method_id":1,"roasting_date":null,"origin_country_id":4,"origin_region_id":null,"webshop_item_link":"https://kava.family/collections/coffee/products/colombia-villa-betulia","origin_farm_id":null,"price_per_gram":0.08,"is_decaf":0,"weight":250,"price":19,"is_removed":0,"currency":"EUR"},{"id":8088,"roaster_id":295,"roasting_level_id":null,"brewing_method_id":3,"processing_method_id":1,"roasting_date":null,"origin_country_id":3,"origin_region_id":1218,"webshop_item_link":"https://www.substancecafe.com/product/ethiopia-burtukaana-goro-bedesa/","origin_farm_id":null,"price_per_gram":0.11,"is_decaf":0,"weight":200,"price":22,"is_removed":0,"currency":"EUR"},{"id":7068,"roaster_id":65,"roasting_level_id":null,"brewing_method_id":2,"processing_method_id":1,"roasting_date":null,"origin_country_id":1,"origin_region_id":1229,"webshop_item_link":"https://heresy.coffee/product/edinson-estela-peru/?lang=en","origin_farm_id":null,"price_per_gram":0.33,"is_decaf":0,"weight":252,"price":82,"is_removed":0,"currency":"PLN"},{"id":2906,"roaster_id":288,"roasting_level_id":null,"brewing_method_id":1,"processing_method_id":1,"roasting_date":null,"origin_country_id":2,"origin_region_id":null,"webshop_item_link":"https://www.nordbeans.com/horizont_z15/","origin_farm_id":null,"price_per_gram":1.04,"is_decaf":0,"weight":250,"price":260,"is_removed":0,"currency":"CZK"},{"id":6701,"roaster_id":47,"roasting_level_id":null,"brewing_method_id":2,"processing_method_id":2,"roasting_date":null,"origin_country_id":4,"origin_region_id":10,"webshop_item_link":"https://www.aprilcoffeeroasters.com/collections/filter-beans/products/el-tesoro-colombia-washed-pink-bourbon","origin_farm_id":null,"price_per_gram":1.67,"is_decaf":0,"weight":125,"price":209,"is_removed":0,"currency":"DKK"},{"id":7742,"roaster_id":307,"roasting_level_id":null,"brewing_method_id":3,"processing_method_id":2,"roasting_date":null,"origin_country_id":537,"origin_region_id":null,"webshop_item_link":"https://www.pomacoffee.com/products/finca-soledad-washed-typica-mejorado","origin_farm_id":null,"price_per_gram":0.22,"is_decaf":0,"weight":150,"price":32.95,"is_removed":0,"currency":"EUR"},{"id":6649,"roaster_id":94,"roasting_level_id":null,"brewing_method_id":2,"processing_method_id":16,"roasting_date":null,"origin_country_id":4,"origin_region_id":175,"webshop_item_link":"https://amatterofconcrete.com/product/rosado/","origin_farm_id":null,"price_per_gram":0.09,"is_decaf":0,"weight":100,"price":9.17,"is_removed":0,"currency":"EUR"}],"originCountries":[4,3],"roasters":[10,11,12,23,27,35,93,94,135,234,252,258,280,283,284,298,300,302,303,305,307,308,318],"tasteNoteGroups":[1]}