{"coffees":[{"id":7529,"roaster_id":10,"roasting_level_id":null,"brewing_method_id":3,"processing_method_id":2,"roasting_date":null,"origin_country_id":4,"origin_region_id":10,"webshop_item_link":"https://lacabra.com/products/hermanos-burbano","origin_farm_id":null,"price_per_gram":0.12,"is_decaf":0,"weight":200,"price":24.95,"is_removed":0,"currency":"EUR"},{"id":6688,"roaster_id":47,"roasting_level_id":null,"brewing_method_id":2,"processing_method_id":2,"roasting_date":null,"origin_country_id":3,"origin_region_id":201,"webshop_item_link":"https://www.aprilcoffeeroasters.com/collections/filter-beans/products/tadesse-ethiopia-washed-krume-74158","origin_farm_id":null,"price_per_gram":1.17,"is_decaf":0,"weight":125,"price":146,"is_removed":0,"currency":"DKK"},{"id":6642,"roaster_id":94,"roasting_level_id":null,"brewing_method_id":2,"processing_method_id":10,"roasting_date":null,"origin_country_id":537,"origin_region_id":null,"webshop_item_link":"https://amatterofconcrete.com/product/sidrawushwush/","origin_farm_id":null,"price_per_gram":0.17,"is_decaf":0,"weight":100,"price":16.97,"is_removed":0,"currency":"EUR"},{"id":7743,"roaster_id":318,"roasting_level_id":null,"brewing_method_id":3,"processing_method_id":1,"roasting_date":null,"origin_country_id":537,"origin_region_id":null,"webshop_item_link":"https://onyxcoffeelab.eu/products/ecuador-la-soledad-typica-natural","origin_farm_id":null,"price_per_gram":0.27,"is_decaf":0,"weight":284,"price":75.95,"is_removed":0,"currency":"EUR"},{"id":7004,"roaster_id":311,"roasting_level_id":null,"brewing_method_id":2,"processing_method_id":22,"roasting_date":null,"origin_country_id":6,"origin_region_id":null,"webshop_item_link":"https://www.doubleshot.cz/en/products/burundi-mikuba-honey-bourbon","origin_farm_id":null,"price_per_gram":1.23,"is_decaf":0,"weight":350,"price":430,"is_removed":0,"currency":"CZK"},{"id":8064,"roaster_id":312,"roasting_level_id":null,"brewing_method_id":2,"processing_method_id":1,"roasting_date":null,"origin_country_id":6,"origin_region_id":null,"webshop_item_link":"https://www.miacoffee.eu/burundi-mubuga-fruit-and-complex-filter-250g/","origin_farm_id":null,"price_per_gram":0.05,"is_decaf":0,"weight":250,"price":12.92,"is_removed":0,"currency":"EUR"},{"id":6934,"roaster_id":310,"roasting_level_id":null,"brewing_method_id":3,"processing_method_id":2,"roasting_date":null,"origin_country_id":3,"origin_region_id":null,"webshop_item_link":"https://www.kofio.co/coffee/ethiopia-jenny-s-barrel-coffee-maturing-in-whiskey-barrels-the-naughty-dog/5601","origin_farm_id":null,"price_per_gram":0.09,"is_decaf":0,"weight":200,"price":17.9,"is_removed":0,"currency":"EUR"},{"id":8057,"roaster_id":312,"roasting_level_id":null,"brewing_method_id":1,"processing_method_id":2,"roasting_date":null,"origin_country_id":540,"origin_region_id":null,"webshop_item_link":"https://www.miacoffee.eu/bolivia-kantutani-fresh-and-balanced-espresso-250g/","origin_farm_id":null,"price_per_gram":0.05,"is_decaf":0,"weight":250,"price":12.5,"is_removed":0,"currency":"EUR"},{"id":6950,"roaster_id":305,"roasting_level_id":null,"brewing_method_id":3,"processing_method_id":10,"roasting_date":null,"origin_country_id":4,"origin_region_id":10,"webshop_item_link":"https://manhattancoffeeroasters.com/product/coffees/rare/hertson-bernal/","origin_farm_id":201,"price_per_gram":0.06,"is_decaf":0,"weight":250,"price":14.98,"is_removed":0,"currency":"EUR"},{"id":7750,"roaster_id":318,"roasting_level_id":null,"brewing_method_id":3,"processing_method_id":2,"roasting_date":null,"origin_country_id":11,"origin_region_id":null,"webshop_item_link":"https://onyxcoffeelab.eu/products/southern-weather-eu","origin_farm_id":null,"price_per_gram":0.1,"is_decaf":0,"weight":113,"price":10.95,"is_removed":0,"currency":"EUR"}],"originCountries":[4,3],"roasters":[10,11,12,23,27,35,93,94,135,234,252,258,280,283,284,298,300,302,303,305,307,308,318],"tasteNoteGroups":[1]}