{"coffees":[{"id":6691,"roaster_id":47,"roasting_level_id":null,"brewing_method_id":2,"processing_method_id":2,"roasting_date":null,"origin_country_id":1,"origin_region_id":1229,"webshop_item_link":"https://www.aprilcoffeeroasters.com/collections/filter-beans/products/peru-ismael-sarango-washed-marshell","origin_farm_id":null,"price_per_gram":0.67,"is_decaf":0,"weight":250,"price":168,"is_removed":0,"currency":"DKK"},{"id":9143,"roaster_id":295,"roasting_level_id":null,"brewing_method_id":3,"processing_method_id":1,"roasting_date":null,"origin_country_id":16,"origin_region_id":230,"webshop_item_link":"https://www.substancecafe.com/product/panama-mi-finquita-geisha-natural/","origin_farm_id":null,"price_per_gram":0.5,"is_decaf":0,"weight":100,"price":50,"is_removed":0,"currency":"EUR"},{"id":7386,"roaster_id":284,"roasting_level_id":null,"brewing_method_id":2,"processing_method_id":1,"roasting_date":null,"origin_country_id":5,"origin_region_id":null,"webshop_item_link":"https://19grams.coffee/products/hermanos-arias-costa-rica-rare-filter-copy","origin_farm_id":null,"price_per_gram":0.2,"is_decaf":0,"weight":200,"price":40.9,"is_removed":0,"currency":"EUR"},{"id":6916,"roaster_id":1,"roasting_level_id":null,"brewing_method_id":3,"processing_method_id":2,"roasting_date":null,"origin_country_id":3,"origin_region_id":304,"webshop_item_link":"https://www.prologcoffee.com/products/bensa-setamo","origin_farm_id":null,"price_per_gram":0.08,"is_decaf":0,"weight":250,"price":19.95,"is_removed":0,"currency":"EUR"},{"id":6013,"roaster_id":82,"roasting_level_id":null,"brewing_method_id":3,"processing_method_id":10,"roasting_date":null,"origin_country_id":14,"origin_region_id":null,"webshop_item_link":"https://shop.spojkaroastery.com/en/products/brewteaful-coffee","origin_farm_id":null,"price_per_gram":0.1,"is_decaf":0,"weight":200,"price":19,"is_removed":0,"currency":"EUR"},{"id":6706,"roaster_id":12,"roasting_level_id":null,"brewing_method_id":3,"processing_method_id":2,"roasting_date":null,"origin_country_id":4,"origin_region_id":131,"webshop_item_link":"https://friedhats.com/products/colombia-las-margaritas-sudan-rume-washed-omni","origin_farm_id":null,"price_per_gram":0.23,"is_decaf":0,"weight":250,"price":56.93,"is_removed":0,"currency":"EUR"},{"id":7387,"roaster_id":284,"roasting_level_id":null,"brewing_method_id":1,"processing_method_id":null,"roasting_date":null,"origin_country_id":539,"origin_region_id":null,"webshop_item_link":"https://19grams.coffee/products/little-flower-classic-espresso","origin_farm_id":null,"price_per_gram":0.04,"is_decaf":0,"weight":250,"price":10.9,"is_removed":0,"currency":"EUR"},{"id":6935,"roaster_id":310,"roasting_level_id":null,"brewing_method_id":2,"processing_method_id":3,"roasting_date":null,"origin_country_id":3,"origin_region_id":134,"webshop_item_link":"https://www.kofio.co/coffee/ethiopia-negele-gorbitu-anaerobic-the-naughty-dog/19848","origin_farm_id":null,"price_per_gram":0.09,"is_decaf":0,"weight":200,"price":17.9,"is_removed":0,"currency":"EUR"},{"id":718,"roaster_id":6,"roasting_level_id":null,"brewing_method_id":4,"processing_method_id":12,"roasting_date":null,"origin_country_id":11,"origin_region_id":null,"webshop_item_link":"https://sheepandraven.com/en/sklep/white-raven/kenya-maguta-natural-nitro-opal/","origin_farm_id":null,"price_per_gram":0.72,"is_decaf":0,"weight":200,"price":145,"is_removed":0,"currency":"PLN"},{"id":6347,"roaster_id":291,"roasting_level_id":null,"brewing_method_id":1,"processing_method_id":1,"roasting_date":null,"origin_country_id":2,"origin_region_id":336,"webshop_item_link":"https://teso.coffee/kawa/sao-pedro/","origin_farm_id":null,"price_per_gram":0.2,"is_decaf":0,"weight":250,"price":49,"is_removed":0,"currency":"PLN"}],"originCountries":[4,3],"roasters":[10,11,12,23,27,35,93,94,135,234,252,258,280,283,284,298,300,302,303,305,307,308,318],"tasteNoteGroups":[1]}