{"coffees":[{"id":481,"roaster_id":252,"roasting_level_id":null,"brewing_method_id":1,"processing_method_id":null,"roasting_date":null,"origin_country_id":16,"origin_region_id":1223,"webshop_item_link":"https://meron.ro/en/produs/panama-ninety-plus-40g-gesha-criolic-folio/","origin_farm_id":null,"price_per_gram":0.75,"is_decaf":0,"weight":40,"price":30.02,"is_removed":0,"currency":"EUR"},{"id":4993,"roaster_id":285,"roasting_level_id":null,"brewing_method_id":3,"processing_method_id":25,"roasting_date":null,"origin_country_id":9,"origin_region_id":null,"webshop_item_link":"https://banibeans.si/products/rwanda-karambi-fully-washed-red-bourbon","origin_farm_id":null,"price_per_gram":0.06,"is_decaf":0,"weight":250,"price":13.9,"is_removed":0,"currency":"EUR"},{"id":4862,"roaster_id":290,"roasting_level_id":null,"brewing_method_id":1,"processing_method_id":10,"roasting_date":null,"origin_country_id":12,"origin_region_id":null,"webshop_item_link":"https://rgbcoffee.pl/products/espresso-special-honduras-el-jardin-anaerobic-250g?variant=52908987056467","origin_farm_id":null,"price_per_gram":0.28,"is_decaf":0,"weight":250,"price":70,"is_removed":0,"currency":"PLN"},{"id":4964,"roaster_id":14,"roasting_level_id":null,"brewing_method_id":3,"processing_method_id":1,"roasting_date":null,"origin_country_id":4,"origin_region_id":175,"webshop_item_link":"https://typika.coffee/collections/kava/products/colombia-santa-maria-el-dragon-decaf-omni-roast","origin_farm_id":null,"price_per_gram":0.06,"is_decaf":1,"weight":250,"price":14.95,"is_removed":0,"currency":"EUR"},{"id":4617,"roaster_id":6,"roasting_level_id":null,"brewing_method_id":4,"processing_method_id":1,"roasting_date":null,"origin_country_id":4,"origin_region_id":175,"webshop_item_link":"https://sheepandraven.com/en/sklep/white-raven/colombia-sudan-rume-amigos/","origin_farm_id":null,"price_per_gram":0.45,"is_decaf":0,"weight":200,"price":89,"is_removed":0,"currency":"PLN"},{"id":3608,"roaster_id":288,"roasting_level_id":null,"brewing_method_id":2,"processing_method_id":1,"roasting_date":null,"origin_country_id":4,"origin_region_id":null,"webshop_item_link":"https://www.nordbeans.com/cocondo-natural_z10/","origin_farm_id":null,"price_per_gram":1.6,"is_decaf":0,"weight":250,"price":400,"is_removed":0,"currency":"CZK"},{"id":80,"roaster_id":39,"roasting_level_id":null,"brewing_method_id":3,"processing_method_id":7,"roasting_date":null,"origin_country_id":2,"origin_region_id":1214,"webshop_item_link":"https://bemybean.pl/produkt/heavy-bean/","origin_farm_id":null,"price_per_gram":0.16,"is_decaf":0,"weight":250,"price":39,"is_removed":0,"currency":"PLN"},{"id":5004,"roaster_id":39,"roasting_level_id":null,"brewing_method_id":3,"processing_method_id":18,"roasting_date":null,"origin_country_id":14,"origin_region_id":null,"webshop_item_link":"https://bemybean.pl/produkt/happy-bean-sumatra/","origin_farm_id":null,"price_per_gram":0.3,"is_decaf":0,"weight":250,"price":76,"is_removed":0,"currency":"PLN"},{"id":471,"roaster_id":252,"roasting_level_id":null,"brewing_method_id":1,"processing_method_id":null,"roasting_date":null,"origin_country_id":16,"origin_region_id":1223,"webshop_item_link":"https://meron.ro/en/produs/panama-janson-lot-1015-200g-gesha-natural/","origin_farm_id":null,"price_per_gram":0.24,"is_decaf":0,"weight":200,"price":48.24,"is_removed":0,"currency":"EUR"},{"id":2432,"roaster_id":286,"roasting_level_id":null,"brewing_method_id":2,"processing_method_id":3,"roasting_date":null,"origin_country_id":4,"origin_region_id":null,"webshop_item_link":"https://stow.si/en/izdelek/la-cabana/","origin_farm_id":null,"price_per_gram":0.07,"is_decaf":0,"weight":250,"price":16.9,"is_removed":0,"currency":"EUR"}],"originCountries":[4,16],"roasters":[11,23,27,35,93,94,135,234,252,258,280,283,284,298,299,300,302],"tasteNoteGroups":[1]}