{"coffees":[{"id":5352,"roaster_id":39,"roasting_level_id":null,"brewing_method_id":2,"processing_method_id":1,"roasting_date":null,"origin_country_id":4,"origin_region_id":10,"webshop_item_link":"https://bemybean.pl/produkt/kolumbia-alirio-rodriguez/","origin_farm_id":null,"price_per_gram":0.32,"is_decaf":0,"weight":250,"price":79,"is_removed":0,"currency":"PLN"},{"id":7433,"roaster_id":39,"roasting_level_id":null,"brewing_method_id":3,"processing_method_id":2,"roasting_date":null,"origin_country_id":8,"origin_region_id":307,"webshop_item_link":"https://bemybean.pl/produkt/nikaragua-jinotega/","origin_farm_id":null,"price_per_gram":0.18,"is_decaf":0,"weight":250,"price":46,"is_removed":0,"currency":"PLN"},{"id":7318,"roaster_id":317,"roasting_level_id":null,"brewing_method_id":3,"processing_method_id":1,"roasting_date":null,"origin_country_id":10,"origin_region_id":1222,"webshop_item_link":"https://lencoffee.com/products/gwatemala-nuevo-oriente","origin_farm_id":null,"price_per_gram":0.33,"is_decaf":0,"weight":100,"price":33,"is_removed":0,"currency":"PLN"},{"id":6351,"roaster_id":6,"roasting_level_id":null,"brewing_method_id":null,"processing_method_id":1,"roasting_date":null,"origin_country_id":10,"origin_region_id":1222,"webshop_item_link":"https://sheepandraven.com/en/sklep/white-sheep/guatemala-nuevo-oriente-natural/","origin_farm_id":null,"price_per_gram":0.29,"is_decaf":0,"weight":200,"price":59,"is_removed":0,"currency":"PLN"},{"id":87,"roaster_id":39,"roasting_level_id":null,"brewing_method_id":3,"processing_method_id":7,"roasting_date":null,"origin_country_id":2,"origin_region_id":1214,"webshop_item_link":"https://bemybean.pl/produkt/boogie-bean-espresso/","origin_farm_id":null,"price_per_gram":0.16,"is_decaf":0,"weight":250,"price":39,"is_removed":0,"currency":"PLN"},{"id":6684,"roaster_id":47,"roasting_level_id":null,"brewing_method_id":2,"processing_method_id":2,"roasting_date":null,"origin_country_id":10,"origin_region_id":null,"webshop_item_link":"https://www.aprilcoffeeroasters.com/collections/filter-beans/products/guatemala-el-socorro-washed-gesha-limited","origin_farm_id":null,"price_per_gram":3.41,"is_decaf":0,"weight":125,"price":426,"is_removed":0,"currency":"DKK"},{"id":6652,"roaster_id":94,"roasting_level_id":null,"brewing_method_id":null,"processing_method_id":2,"roasting_date":null,"origin_country_id":10,"origin_region_id":173,"webshop_item_link":"https://amatterofconcrete.com/product/022/","origin_farm_id":null,"price_per_gram":0.06,"is_decaf":0,"weight":240,"price":14.04,"is_removed":0,"currency":"EUR"},{"id":6683,"roaster_id":47,"roasting_level_id":null,"brewing_method_id":1,"processing_method_id":2,"roasting_date":null,"origin_country_id":10,"origin_region_id":173,"webshop_item_link":"https://www.aprilcoffeeroasters.com/collections/espresso-beans/products/el-morito-washed-pacamara","origin_farm_id":null,"price_per_gram":1.01,"is_decaf":0,"weight":250,"price":252,"is_removed":0,"currency":"DKK"},{"id":85,"roaster_id":39,"roasting_level_id":null,"brewing_method_id":2,"processing_method_id":8,"roasting_date":null,"origin_country_id":4,"origin_region_id":null,"webshop_item_link":"https://bemybean.pl/produkt/decaf-filter-kolumbia-popayan/","origin_farm_id":null,"price_per_gram":0.6,"is_decaf":1,"weight":250,"price":149,"is_removed":0,"currency":"PLN"},{"id":6700,"roaster_id":47,"roasting_level_id":null,"brewing_method_id":2,"processing_method_id":2,"roasting_date":null,"origin_country_id":10,"origin_region_id":173,"webshop_item_link":"https://www.aprilcoffeeroasters.com/collections/filter-beans/products/el-morito-guatemala-washed-pacamara","origin_farm_id":null,"price_per_gram":1.36,"is_decaf":0,"weight":125,"price":170,"is_removed":0,"currency":"DKK"}],"originCountries":[10],"roasters":[39],"tasteNoteGroups":[]}