[{"currency_code":"AED","rate":3.6725},{"currency_code":"AFN","rate":63.749997},{"currency_code":"ALL","rate":81.050332},{"currency_code":"AMD","rate":372.572592},{"currency_code":"ANG","rate":1.79},{"currency_code":"AOA","rate":913.11575},{"currency_code":"ARS","rate":1376.9023},{"currency_code":"AUD","rate":1.398217},{"currency_code":"AWG","rate":1.8},{"currency_code":"AZN","rate":1.7},{"currency_code":"BAM","rate":1.659926},{"currency_code":"BBD","rate":2},{"currency_code":"BDT","rate":122.580609},{"currency_code":"BGN","rate":1.663246},{"currency_code":"BHD","rate":0.377134},{"currency_code":"BIF","rate":2975.450996},{"currency_code":"BMD","rate":1},{"currency_code":"BND","rate":1.269716},{"currency_code":"BOB","rate":6.928101},{"currency_code":"BRL","rate":4.9605},{"currency_code":"BSD","rate":1},{"currency_code":"BTC","rate":0.000013090912},{"currency_code":"BTN","rate":93.104298},{"currency_code":"BWP","rate":13.393251},{"currency_code":"BYN","rate":2.833537},{"currency_code":"BZD","rate":2.009115},{"currency_code":"CAD","rate":1.366075},{"currency_code":"CDF","rate":2327.642026},{"currency_code":"CHF","rate":0.779765},{"currency_code":"CLF","rate":0.022403},{"currency_code":"CLP","rate":884.955752},{"currency_code":"CNH","rate":6.816677},{"currency_code":"CNY","rate":6.8162},{"currency_code":"COP","rate":3609.241434},{"currency_code":"CRC","rate":455.158689},{"currency_code":"CUC","rate":1},{"currency_code":"CUP","rate":25.75},{"currency_code":"CVE","rate":93.584083},{"currency_code":"CZK","rate":20.6682},{"currency_code":"DJF","rate":177.894954},{"currency_code":"DKK","rate":6.355138},{"currency_code":"DOP","rate":60.10507},{"currency_code":"DZD","rate":132.180332},{"currency_code":"EGP","rate":51.772114},{"currency_code":"ERN","rate":15},{"currency_code":"ETB","rate":155.405365},{"currency_code":"EUR","rate":0.850383},{"currency_code":"FJD","rate":2.19785},{"currency_code":"FKP","rate":0.740596},{"currency_code":"GBP","rate":0.740596},{"currency_code":"GEL","rate":2.685},{"currency_code":"GGP","rate":0.740596},{"currency_code":"GHS","rate":11.0393},{"currency_code":"GIP","rate":0.740596},{"currency_code":"GMD","rate":73.166669},{"currency_code":"GNF","rate":8764.515873},{"currency_code":"GTQ","rate":7.643664},{"currency_code":"GYD","rate":209.00576},{"currency_code":"HKD","rate":7.83072},{"currency_code":"HNL","rate":26.542928},{"currency_code":"HRK","rate":6.40737},{"currency_code":"HTG","rate":130.81168},{"currency_code":"HUF","rate":307.958177},{"currency_code":"IDR","rate":17150.662952},{"currency_code":"ILS","rate":2.989685},{"currency_code":"IMP","rate":0.740596},{"currency_code":"INR","rate":93.406876},{"currency_code":"IQD","rate":1308.686358},{"currency_code":"IRR","rate":1323000},{"currency_code":"ISK","rate":121.77},{"currency_code":"JEP","rate":0.740596},{"currency_code":"JMD","rate":158.247609},{"currency_code":"JOD","rate":0.709},{"currency_code":"JPY","rate":159.20255882},{"currency_code":"KES","rate":129.2},{"currency_code":"KGS","rate":87.45},{"currency_code":"KHR","rate":4000.605852},{"currency_code":"KMF","rate":418.000279},{"currency_code":"KPW","rate":900},{"currency_code":"KRW","rate":1470.341407},{"currency_code":"KWD","rate":0.30826},{"currency_code":"KYD","rate":0.832485},{"currency_code":"KZT","rate":465.941826},{"currency_code":"LAK","rate":22040.597331},{"currency_code":"LBP","rate":89471.453014},{"currency_code":"LKR","rate":316.121901},{"currency_code":"LRD","rate":184.249969},{"currency_code":"LSL","rate":16.35859},{"currency_code":"LYD","rate":6.331263},{"currency_code":"MAD","rate":9.226434},{"currency_code":"MDL","rate":17.199962},{"currency_code":"MGA","rate":4133.118741},{"currency_code":"MKD","rate":52.430362},{"currency_code":"MMK","rate":2099.81},{"currency_code":"MNT","rate":3569.47},{"currency_code":"MOP","rate":8.057338},{"currency_code":"MRU","rate":39.868621},{"currency_code":"MUR","rate":46.369997},{"currency_code":"MVR","rate":15.45},{"currency_code":"MWK","rate":1732.18208},{"currency_code":"MXN","rate":17.322557},{"currency_code":"MYR","rate":3.951},{"currency_code":"MZN","rate":63.955002},{"currency_code":"NAD","rate":16.35859},{"currency_code":"NGN","rate":1346.61},{"currency_code":"NIO","rate":36.76561},{"currency_code":"NOK","rate":9.337579},{"currency_code":"NPR","rate":148.84577},{"currency_code":"NZD","rate":1.694261},{"currency_code":"OMR","rate":0.384503},{"currency_code":"PAB","rate":1},{"currency_code":"PEN","rate":3.429932},{"currency_code":"PGK","rate":4.392051},{"currency_code":"PHP","rate":59.885168},{"currency_code":"PKR","rate":278.536876},{"currency_code":"PLN","rate":3.597817},{"currency_code":"PYG","rate":6369.381625},{"currency_code":"QAR","rate":3.642581},{"currency_code":"RON","rate":4.3361},{"currency_code":"RSD","rate":99.833557},{"currency_code":"RUB","rate":74.600978},{"currency_code":"RWF","rate":1463.489336},{"currency_code":"SAR","rate":3.750861},{"currency_code":"SBD","rate":8.038715},{"currency_code":"SCR","rate":13.978897},{"currency_code":"SDG","rate":601},{"currency_code":"SEK","rate":9.157505},{"currency_code":"SGD","rate":1.272066},{"currency_code":"SHP","rate":0.740596},{"currency_code":"SLE","rate":24.65},{"currency_code":"SLL","rate":20969.5},{"currency_code":"SOS","rate":570.917453},{"currency_code":"SRD","rate":37.449},{"currency_code":"SSP","rate":130.26},{"currency_code":"STD","rate":22281.8},{"currency_code":"STN","rate":20.793285},{"currency_code":"SVC","rate":8.740707},{"currency_code":"SYP","rate":13002},{"currency_code":"SZL","rate":16.354347},{"currency_code":"THB","rate":32.1015},{"currency_code":"TJS","rate":9.467984},{"currency_code":"TMT","rate":3.505},{"currency_code":"TND","rate":2.891367},{"currency_code":"TOP","rate":2.40776},{"currency_code":"TRY","rate":44.894423},{"currency_code":"TTD","rate":6.779373},{"currency_code":"TWD","rate":31.429502},{"currency_code":"TZS","rate":2605.425},{"currency_code":"UAH","rate":44.124652},{"currency_code":"UGX","rate":3701.277284},{"currency_code":"USD","rate":1},{"currency_code":"UYU","rate":39.759763},{"currency_code":"UZS","rate":12085.404603},{"currency_code":"VES","rate":480.631207},{"currency_code":"VND","rate":26329.676388},{"currency_code":"VUV","rate":119.389},{"currency_code":"WST","rate":2.74422},{"currency_code":"XAF","rate":557.814729},{"currency_code":"XAG","rate":0.01266618},{"currency_code":"XAU","rate":0.00020904},{"currency_code":"XCD","rate":2.70255},{"currency_code":"XCG","rate":1.800421},{"currency_code":"XDR","rate":0.692365},{"currency_code":"XOF","rate":557.814729},{"currency_code":"XPD","rate":0.00064396},{"currency_code":"XPF","rate":101.477694},{"currency_code":"XPT","rate":0.00048185},{"currency_code":"YER","rate":238.649953},{"currency_code":"ZAR","rate":16.366615},{"currency_code":"ZMW","rate":18.905523},{"currency_code":"ZWG","rate":25.3626},{"currency_code":"ZWL","rate":322}]