[{"currency_code":"AED","rate":3.6725},{"currency_code":"AFN","rate":63.999997},{"currency_code":"ALL","rate":82.728471},{"currency_code":"AMD","rate":366.579494},{"currency_code":"ANG","rate":1.79},{"currency_code":"AOA","rate":912.0475},{"currency_code":"ARS","rate":1477.2705},{"currency_code":"AUD","rate":1.449013},{"currency_code":"AWG","rate":1.8},{"currency_code":"AZN","rate":1.7},{"currency_code":"BAM","rate":1.717648},{"currency_code":"BBD","rate":2},{"currency_code":"BDT","rate":122.557405},{"currency_code":"BGN","rate":1.71434},{"currency_code":"BHD","rate":0.375703},{"currency_code":"BIF","rate":2974.7745},{"currency_code":"BMD","rate":1},{"currency_code":"BND","rate":1.292776},{"currency_code":"BOB","rate":6.885468},{"currency_code":"BRL","rate":5.1771},{"currency_code":"BSD","rate":1},{"currency_code":"BTC","rate":0.000016772363},{"currency_code":"BTN","rate":94.011396},{"currency_code":"BWP","rate":13.596624},{"currency_code":"BYN","rate":2.835714},{"currency_code":"BZD","rate":2.004022},{"currency_code":"CAD","rate":1.41855},{"currency_code":"CDF","rate":2294.682684},{"currency_code":"CHF","rate":0.808123},{"currency_code":"CLF","rate":0.023345},{"currency_code":"CLP","rate":918.81},{"currency_code":"CNH","rate":6.80119},{"currency_code":"CNY","rate":6.7999},{"currency_code":"COP","rate":3408.048488},{"currency_code":"CRC","rate":453.513826},{"currency_code":"CUC","rate":1},{"currency_code":"CUP","rate":25.75},{"currency_code":"CVE","rate":96.839638},{"currency_code":"CZK","rate":21.2628},{"currency_code":"DJF","rate":177.43588},{"currency_code":"DKK","rate":6.552969},{"currency_code":"DOP","rate":58.717884},{"currency_code":"DZD","rate":133.277367},{"currency_code":"EGP","rate":49.5074},{"currency_code":"ERN","rate":15},{"currency_code":"ETB","rate":157.152203},{"currency_code":"EUR","rate":0.876658},{"currency_code":"FJD","rate":2.2661},{"currency_code":"FKP","rate":0.756448},{"currency_code":"GBP","rate":0.756448},{"currency_code":"GEL","rate":2.645},{"currency_code":"GGP","rate":0.756448},{"currency_code":"GHS","rate":11.207328},{"currency_code":"GIP","rate":0.756448},{"currency_code":"GMD","rate":73.000001},{"currency_code":"GNF","rate":8731.285852},{"currency_code":"GTQ","rate":7.602085},{"currency_code":"GYD","rate":208.487386},{"currency_code":"HKD","rate":7.842647},{"currency_code":"HNL","rate":26.661925},{"currency_code":"HRK","rate":6.604194},{"currency_code":"HTG","rate":130.236038},{"currency_code":"HUF","rate":310.038693},{"currency_code":"IDR","rate":17881.04716},{"currency_code":"ILS","rate":2.99554},{"currency_code":"IMP","rate":0.756448},{"currency_code":"INR","rate":94.297738},{"currency_code":"IQD","rate":1305.337076},{"currency_code":"IRR","rate":1375050},{"currency_code":"ISK","rate":126.24},{"currency_code":"JEP","rate":0.756448},{"currency_code":"JMD","rate":157.043562},{"currency_code":"JOD","rate":0.709},{"currency_code":"JPY","rate":161.60904545},{"currency_code":"KES","rate":129.41},{"currency_code":"KGS","rate":87.45},{"currency_code":"KHR","rate":4012.742384},{"currency_code":"KMF","rate":433.999972},{"currency_code":"KPW","rate":900},{"currency_code":"KRW","rate":1537.350279},{"currency_code":"KWD","rate":0.309577},{"currency_code":"KYD","rate":0.830384},{"currency_code":"KZT","rate":482.931207},{"currency_code":"LAK","rate":22145.800359},{"currency_code":"LBP","rate":89239.356575},{"currency_code":"LKR","rate":335.815936},{"currency_code":"LRD","rate":181.34474},{"currency_code":"LSL","rate":16.501409},{"currency_code":"LYD","rate":6.398721},{"currency_code":"MAD","rate":9.380747},{"currency_code":"MDL","rate":17.687045},{"currency_code":"MGA","rate":4247.934139},{"currency_code":"MKD","rate":54.044459},{"currency_code":"MMK","rate":2099.81},{"currency_code":"MNT","rate":3569.47},{"currency_code":"MOP","rate":8.04681},{"currency_code":"MRU","rate":39.577927},{"currency_code":"MUR","rate":47.709998},{"currency_code":"MVR","rate":15.45},{"currency_code":"MWK","rate":1727.811023},{"currency_code":"MXN","rate":17.524767},{"currency_code":"MYR","rate":4.0875},{"currency_code":"MZN","rate":63.899993},{"currency_code":"NAD","rate":16.501409},{"currency_code":"NGN","rate":1374.84},{"currency_code":"NIO","rate":36.667034},{"currency_code":"NOK","rate":9.896186},{"currency_code":"NPR","rate":150.417355},{"currency_code":"NZD","rate":1.768866},{"currency_code":"OMR","rate":0.384499},{"currency_code":"PAB","rate":1},{"currency_code":"PEN","rate":3.409915},{"currency_code":"PGK","rate":4.372665},{"currency_code":"PHP","rate":61.235998},{"currency_code":"PKR","rate":277.300373},{"currency_code":"PLN","rate":3.755714},{"currency_code":"PYG","rate":6088.747595},{"currency_code":"QAR","rate":3.632156},{"currency_code":"RON","rate":4.5938},{"currency_code":"RSD","rate":102.896763},{"currency_code":"RUB","rate":77.600691},{"currency_code":"RWF","rate":1464.258346},{"currency_code":"SAR","rate":3.747799},{"currency_code":"SBD","rate":8.051953},{"currency_code":"SCR","rate":14.043424},{"currency_code":"SDG","rate":600},{"currency_code":"SEK","rate":9.696478},{"currency_code":"SGD","rate":1.293665},{"currency_code":"SHP","rate":0.756448},{"currency_code":"SLE","rate":24.75},{"currency_code":"SLL","rate":20969.5},{"currency_code":"SOS","rate":569.439413},{"currency_code":"SRD","rate":37.32},{"currency_code":"SSP","rate":130.26},{"currency_code":"STD","rate":22281.8},{"currency_code":"STN","rate":21.516425},{"currency_code":"SVC","rate":8.71925},{"currency_code":"SYP","rate":13002},{"currency_code":"SZL","rate":16.499146},{"currency_code":"THB","rate":33.3645},{"currency_code":"TJS","rate":9.216885},{"currency_code":"TMT","rate":3.5},{"currency_code":"TND","rate":2.958631},{"currency_code":"TOP","rate":2.40776},{"currency_code":"TRY","rate":46.624808},{"currency_code":"TTD","rate":6.767782},{"currency_code":"TWD","rate":31.846974},{"currency_code":"TZS","rate":2623.403},{"currency_code":"UAH","rate":44.804218},{"currency_code":"UGX","rate":3686.905621},{"currency_code":"USD","rate":1},{"currency_code":"UYU","rate":40.150739},{"currency_code":"UZS","rate":11969.556972},{"currency_code":"VES","rate":620.752846},{"currency_code":"VND","rate":26298.488292},{"currency_code":"VUV","rate":119.389},{"currency_code":"WST","rate":2.74422},{"currency_code":"XAF","rate":575.050019},{"currency_code":"XAG","rate":0.01717726},{"currency_code":"XAU","rate":0.00024708},{"currency_code":"XCD","rate":2.70255},{"currency_code":"XCG","rate":1.795842},{"currency_code":"XDR","rate":0.716453},{"currency_code":"XOF","rate":575.050019},{"currency_code":"XPD","rate":0.00082986},{"currency_code":"XPF","rate":104.613139},{"currency_code":"XPT","rate":0.00062316},{"currency_code":"YER","rate":238.624958},{"currency_code":"ZAR","rate":16.437259},{"currency_code":"ZMW","rate":17.985175},{"currency_code":"ZWG","rate":25.3626},{"currency_code":"ZWL","rate":322}]